{
  "id": "e189e241-aaa6-4b7f-9a0b-45267fa0daef",
  "prevId": "8e5223be-eb6c-4801-8c9a-9cc6bfef5845",
  "version": "7",
  "dialect": "postgresql",
  "tables": {
    "public.property": {
      "name": "property",
      "schema": "",
      "columns": {
        "id": {
          "name": "id",
          "type": "uuid",
          "primaryKey": true,
          "notNull": true,
          "default": "gen_random_uuid()"
        },
        "title": {
          "name": "title",
          "type": "text",
          "primaryKey": false,
          "notNull": true
        },
        "description": {
          "name": "description",
          "type": "text",
          "primaryKey": false,
          "notNull": true
        },
        "price": {
          "name": "price",
          "type": "numeric",
          "primaryKey": false,
          "notNull": true
        },
        "currency": {
          "name": "currency",
          "type": "text",
          "primaryKey": false,
          "notNull": true,
          "default": "'INR'"
        },
        "type": {
          "name": "type",
          "type": "text",
          "primaryKey": false,
          "notNull": true
        },
        "bhk": {
          "name": "bhk",
          "type": "integer",
          "primaryKey": false,
          "notNull": true
        },
        "baths": {
          "name": "baths",
          "type": "integer",
          "primaryKey": false,
          "notNull": true
        },
        "area": {
          "name": "area",
          "type": "integer",
          "primaryKey": false,
          "notNull": true
        },
        "ownerId": {
          "name": "ownerId",
          "type": "uuid",
          "primaryKey": false,
          "notNull": false
        },
        "listed_by_id": {
          "name": "listed_by_id",
          "type": "uuid",
          "primaryKey": false,
          "notNull": false
        },
        "created_at": {
          "name": "created_at",
          "type": "timestamp with time zone",
          "primaryKey": false,
          "notNull": false,
          "default": "now()"
        },
        "updated_at": {
          "name": "updated_at",
          "type": "timestamp with time zone",
          "primaryKey": false,
          "notNull": false,
          "default": "now()"
        }
      },
      "indexes": {
        "property_owner_idx": {
          "name": "property_owner_idx",
          "columns": [
            {
              "expression": "ownerId",
              "isExpression": false,
              "asc": true,
              "nulls": "last"
            }
          ],
          "isUnique": false,
          "concurrently": false,
          "method": "btree",
          "with": {}
        },
        "property_listed_by__idx": {
          "name": "property_listed_by__idx",
          "columns": [
            {
              "expression": "listed_by_id",
              "isExpression": false,
              "asc": true,
              "nulls": "last"
            }
          ],
          "isUnique": false,
          "concurrently": false,
          "method": "btree",
          "with": {}
        },
        "property_price__idx": {
          "name": "property_price__idx",
          "columns": [
            {
              "expression": "price",
              "isExpression": false,
              "asc": true,
              "nulls": "last"
            }
          ],
          "isUnique": false,
          "concurrently": false,
          "method": "btree",
          "with": {}
        },
        "property_bhk__idx": {
          "name": "property_bhk__idx",
          "columns": [
            {
              "expression": "bhk",
              "isExpression": false,
              "asc": true,
              "nulls": "last"
            }
          ],
          "isUnique": false,
          "concurrently": false,
          "method": "btree",
          "with": {}
        },
        "property_baths__idx": {
          "name": "property_baths__idx",
          "columns": [
            {
              "expression": "baths",
              "isExpression": false,
              "asc": true,
              "nulls": "last"
            }
          ],
          "isUnique": false,
          "concurrently": false,
          "method": "btree",
          "with": {}
        },
        "property_area__idx": {
          "name": "property_area__idx",
          "columns": [
            {
              "expression": "area",
              "isExpression": false,
              "asc": true,
              "nulls": "last"
            }
          ],
          "isUnique": false,
          "concurrently": false,
          "method": "btree",
          "with": {}
        },
        "property_type__idx": {
          "name": "property_type__idx",
          "columns": [
            {
              "expression": "type",
              "isExpression": false,
              "asc": true,
              "nulls": "last"
            }
          ],
          "isUnique": false,
          "concurrently": false,
          "method": "btree",
          "with": {}
        },
        "property_created__idx": {
          "name": "property_created__idx",
          "columns": [
            {
              "expression": "created_at",
              "isExpression": false,
              "asc": true,
              "nulls": "last"
            }
          ],
          "isUnique": false,
          "concurrently": false,
          "method": "btree",
          "with": {}
        },
        "property_title__idx": {
          "name": "property_title__idx",
          "columns": [
            {
              "expression": "title",
              "isExpression": false,
              "asc": true,
              "nulls": "last"
            }
          ],
          "isUnique": false,
          "concurrently": false,
          "method": "btree",
          "with": {}
        },
        "property_description__idx": {
          "name": "property_description__idx",
          "columns": [
            {
              "expression": "description",
              "isExpression": false,
              "asc": true,
              "nulls": "last"
            }
          ],
          "isUnique": false,
          "concurrently": false,
          "method": "btree",
          "with": {}
        }
      },
      "foreignKeys": {
        "property_ownerId_users_id_fk": {
          "name": "property_ownerId_users_id_fk",
          "tableFrom": "property",
          "tableTo": "users",
          "columnsFrom": [
            "ownerId"
          ],
          "columnsTo": [
            "id"
          ],
          "onDelete": "cascade",
          "onUpdate": "cascade"
        },
        "property_listed_by_id_users_id_fk": {
          "name": "property_listed_by_id_users_id_fk",
          "tableFrom": "property",
          "tableTo": "users",
          "columnsFrom": [
            "listed_by_id"
          ],
          "columnsTo": [
            "id"
          ],
          "onDelete": "set null",
          "onUpdate": "no action"
        }
      },
      "compositePrimaryKeys": {},
      "uniqueConstraints": {},
      "policies": {},
      "checkConstraints": {},
      "isRLSEnabled": false
    },
    "public.property_address": {
      "name": "property_address",
      "schema": "",
      "columns": {
        "id": {
          "name": "id",
          "type": "uuid",
          "primaryKey": true,
          "notNull": true,
          "default": "gen_random_uuid()"
        },
        "propertyId": {
          "name": "propertyId",
          "type": "uuid",
          "primaryKey": false,
          "notNull": false
        },
        "locality": {
          "name": "locality",
          "type": "text",
          "primaryKey": false,
          "notNull": true
        },
        "city": {
          "name": "city",
          "type": "text",
          "primaryKey": false,
          "notNull": true
        },
        "state": {
          "name": "state",
          "type": "text",
          "primaryKey": false,
          "notNull": true
        }
      },
      "indexes": {
        "property_address_property_id_idx": {
          "name": "property_address_property_id_idx",
          "columns": [
            {
              "expression": "propertyId",
              "isExpression": false,
              "asc": true,
              "nulls": "last"
            }
          ],
          "isUnique": false,
          "concurrently": false,
          "method": "btree",
          "with": {}
        },
        "property_address_locality_idx": {
          "name": "property_address_locality_idx",
          "columns": [
            {
              "expression": "locality",
              "isExpression": false,
              "asc": true,
              "nulls": "last"
            }
          ],
          "isUnique": false,
          "concurrently": false,
          "method": "btree",
          "with": {}
        },
        "property_address_city_idx": {
          "name": "property_address_city_idx",
          "columns": [
            {
              "expression": "city",
              "isExpression": false,
              "asc": true,
              "nulls": "last"
            }
          ],
          "isUnique": false,
          "concurrently": false,
          "method": "btree",
          "with": {}
        },
        "property_address_state_idx": {
          "name": "property_address_state_idx",
          "columns": [
            {
              "expression": "state",
              "isExpression": false,
              "asc": true,
              "nulls": "last"
            }
          ],
          "isUnique": false,
          "concurrently": false,
          "method": "btree",
          "with": {}
        }
      },
      "foreignKeys": {
        "property_address_propertyId_property_id_fk": {
          "name": "property_address_propertyId_property_id_fk",
          "tableFrom": "property_address",
          "tableTo": "property",
          "columnsFrom": [
            "propertyId"
          ],
          "columnsTo": [
            "id"
          ],
          "onDelete": "cascade",
          "onUpdate": "cascade"
        }
      },
      "compositePrimaryKeys": {},
      "uniqueConstraints": {},
      "policies": {},
      "checkConstraints": {},
      "isRLSEnabled": false
    },
    "public.property_amenities": {
      "name": "property_amenities",
      "schema": "",
      "columns": {
        "id": {
          "name": "id",
          "type": "uuid",
          "primaryKey": true,
          "notNull": true,
          "default": "gen_random_uuid()"
        },
        "propertyId": {
          "name": "propertyId",
          "type": "uuid",
          "primaryKey": false,
          "notNull": false
        },
        "name": {
          "name": "name",
          "type": "text",
          "primaryKey": false,
          "notNull": true
        }
      },
      "indexes": {
        "property_amenities_property_id_idx": {
          "name": "property_amenities_property_id_idx",
          "columns": [
            {
              "expression": "propertyId",
              "isExpression": false,
              "asc": true,
              "nulls": "last"
            }
          ],
          "isUnique": false,
          "concurrently": false,
          "method": "btree",
          "with": {}
        },
        "property_amenities_name_idx": {
          "name": "property_amenities_name_idx",
          "columns": [
            {
              "expression": "name",
              "isExpression": false,
              "asc": true,
              "nulls": "last"
            }
          ],
          "isUnique": false,
          "concurrently": false,
          "method": "btree",
          "with": {}
        }
      },
      "foreignKeys": {
        "property_amenities_propertyId_property_id_fk": {
          "name": "property_amenities_propertyId_property_id_fk",
          "tableFrom": "property_amenities",
          "tableTo": "property",
          "columnsFrom": [
            "propertyId"
          ],
          "columnsTo": [
            "id"
          ],
          "onDelete": "cascade",
          "onUpdate": "cascade"
        }
      },
      "compositePrimaryKeys": {},
      "uniqueConstraints": {},
      "policies": {},
      "checkConstraints": {},
      "isRLSEnabled": false
    },
    "public.property_details": {
      "name": "property_details",
      "schema": "",
      "columns": {
        "id": {
          "name": "id",
          "type": "uuid",
          "primaryKey": true,
          "notNull": true,
          "default": "gen_random_uuid()"
        },
        "propertyId": {
          "name": "propertyId",
          "type": "uuid",
          "primaryKey": false,
          "notNull": false
        },
        "possessionStatus": {
          "name": "possessionStatus",
          "type": "text",
          "primaryKey": false,
          "notNull": false
        },
        "listedBy": {
          "name": "listedBy",
          "type": "text",
          "primaryKey": false,
          "notNull": false
        },
        "furnishedStatus": {
          "name": "furnishedStatus",
          "type": "text",
          "primaryKey": false,
          "notNull": false
        }
      },
      "indexes": {
        "property_details_property_id_idx": {
          "name": "property_details_property_id_idx",
          "columns": [
            {
              "expression": "propertyId",
              "isExpression": false,
              "asc": true,
              "nulls": "last"
            }
          ],
          "isUnique": false,
          "concurrently": false,
          "method": "btree",
          "with": {}
        },
        "property_details_possession_idx": {
          "name": "property_details_possession_idx",
          "columns": [
            {
              "expression": "possessionStatus",
              "isExpression": false,
              "asc": true,
              "nulls": "last"
            }
          ],
          "isUnique": false,
          "concurrently": false,
          "method": "btree",
          "with": {}
        },
        "property_details_listed_by_idx": {
          "name": "property_details_listed_by_idx",
          "columns": [
            {
              "expression": "listedBy",
              "isExpression": false,
              "asc": true,
              "nulls": "last"
            }
          ],
          "isUnique": false,
          "concurrently": false,
          "method": "btree",
          "with": {}
        },
        "property_details_furnished_idx": {
          "name": "property_details_furnished_idx",
          "columns": [
            {
              "expression": "furnishedStatus",
              "isExpression": false,
              "asc": true,
              "nulls": "last"
            }
          ],
          "isUnique": false,
          "concurrently": false,
          "method": "btree",
          "with": {}
        }
      },
      "foreignKeys": {
        "property_details_propertyId_property_id_fk": {
          "name": "property_details_propertyId_property_id_fk",
          "tableFrom": "property_details",
          "tableTo": "property",
          "columnsFrom": [
            "propertyId"
          ],
          "columnsTo": [
            "id"
          ],
          "onDelete": "cascade",
          "onUpdate": "cascade"
        }
      },
      "compositePrimaryKeys": {},
      "uniqueConstraints": {},
      "policies": {},
      "checkConstraints": {},
      "isRLSEnabled": false
    },
    "public.property_enquiry": {
      "name": "property_enquiry",
      "schema": "",
      "columns": {
        "id": {
          "name": "id",
          "type": "uuid",
          "primaryKey": true,
          "notNull": true,
          "default": "gen_random_uuid()"
        },
        "userId": {
          "name": "userId",
          "type": "uuid",
          "primaryKey": false,
          "notNull": false
        },
        "propertyId": {
          "name": "propertyId",
          "type": "uuid",
          "primaryKey": false,
          "notNull": false
        },
        "message": {
          "name": "message",
          "type": "text",
          "primaryKey": false,
          "notNull": true
        },
        "created_at": {
          "name": "created_at",
          "type": "timestamp with time zone",
          "primaryKey": false,
          "notNull": false,
          "default": "now()"
        },
        "updated_at": {
          "name": "updated_at",
          "type": "timestamp with time zone",
          "primaryKey": false,
          "notNull": false,
          "default": "now()"
        }
      },
      "indexes": {
        "property_enquiry_user_id_idx": {
          "name": "property_enquiry_user_id_idx",
          "columns": [
            {
              "expression": "userId",
              "isExpression": false,
              "asc": true,
              "nulls": "last"
            }
          ],
          "isUnique": false,
          "concurrently": false,
          "method": "btree",
          "with": {}
        },
        "property_enquiry_property_id_idx": {
          "name": "property_enquiry_property_id_idx",
          "columns": [
            {
              "expression": "propertyId",
              "isExpression": false,
              "asc": true,
              "nulls": "last"
            }
          ],
          "isUnique": false,
          "concurrently": false,
          "method": "btree",
          "with": {}
        },
        "property_enquiry_property_created_idx": {
          "name": "property_enquiry_property_created_idx",
          "columns": [
            {
              "expression": "created_at",
              "isExpression": false,
              "asc": true,
              "nulls": "last"
            }
          ],
          "isUnique": false,
          "concurrently": false,
          "method": "btree",
          "with": {}
        }
      },
      "foreignKeys": {
        "property_enquiry_userId_users_id_fk": {
          "name": "property_enquiry_userId_users_id_fk",
          "tableFrom": "property_enquiry",
          "tableTo": "users",
          "columnsFrom": [
            "userId"
          ],
          "columnsTo": [
            "id"
          ],
          "onDelete": "cascade",
          "onUpdate": "cascade"
        },
        "property_enquiry_propertyId_property_id_fk": {
          "name": "property_enquiry_propertyId_property_id_fk",
          "tableFrom": "property_enquiry",
          "tableTo": "property",
          "columnsFrom": [
            "propertyId"
          ],
          "columnsTo": [
            "id"
          ],
          "onDelete": "cascade",
          "onUpdate": "cascade"
        }
      },
      "compositePrimaryKeys": {},
      "uniqueConstraints": {},
      "policies": {},
      "checkConstraints": {},
      "isRLSEnabled": false
    },
    "public.property_favorites": {
      "name": "property_favorites",
      "schema": "",
      "columns": {
        "id": {
          "name": "id",
          "type": "uuid",
          "primaryKey": true,
          "notNull": true,
          "default": "gen_random_uuid()"
        },
        "propertyId": {
          "name": "propertyId",
          "type": "uuid",
          "primaryKey": false,
          "notNull": false
        },
        "userId": {
          "name": "userId",
          "type": "uuid",
          "primaryKey": false,
          "notNull": true
        },
        "created_at": {
          "name": "created_at",
          "type": "timestamp with time zone",
          "primaryKey": false,
          "notNull": false,
          "default": "now()"
        },
        "updated_at": {
          "name": "updated_at",
          "type": "timestamp with time zone",
          "primaryKey": false,
          "notNull": false,
          "default": "now()"
        }
      },
      "indexes": {
        "property_favorites_unique_idx": {
          "name": "property_favorites_unique_idx",
          "columns": [
            {
              "expression": "propertyId",
              "isExpression": false,
              "asc": true,
              "nulls": "last"
            },
            {
              "expression": "userId",
              "isExpression": false,
              "asc": true,
              "nulls": "last"
            }
          ],
          "isUnique": true,
          "concurrently": false,
          "method": "btree",
          "with": {}
        },
        "property_favorites_user_id_idx": {
          "name": "property_favorites_user_id_idx",
          "columns": [
            {
              "expression": "userId",
              "isExpression": false,
              "asc": true,
              "nulls": "last"
            }
          ],
          "isUnique": false,
          "concurrently": false,
          "method": "btree",
          "with": {}
        }
      },
      "foreignKeys": {
        "property_favorites_propertyId_property_id_fk": {
          "name": "property_favorites_propertyId_property_id_fk",
          "tableFrom": "property_favorites",
          "tableTo": "property",
          "columnsFrom": [
            "propertyId"
          ],
          "columnsTo": [
            "id"
          ],
          "onDelete": "cascade",
          "onUpdate": "cascade"
        },
        "property_favorites_userId_users_id_fk": {
          "name": "property_favorites_userId_users_id_fk",
          "tableFrom": "property_favorites",
          "tableTo": "users",
          "columnsFrom": [
            "userId"
          ],
          "columnsTo": [
            "id"
          ],
          "onDelete": "cascade",
          "onUpdate": "cascade"
        }
      },
      "compositePrimaryKeys": {},
      "uniqueConstraints": {},
      "policies": {},
      "checkConstraints": {},
      "isRLSEnabled": false
    },
    "public.property_images": {
      "name": "property_images",
      "schema": "",
      "columns": {
        "id": {
          "name": "id",
          "type": "uuid",
          "primaryKey": true,
          "notNull": true,
          "default": "gen_random_uuid()"
        },
        "propertyId": {
          "name": "propertyId",
          "type": "uuid",
          "primaryKey": false,
          "notNull": false
        },
        "url": {
          "name": "url",
          "type": "text",
          "primaryKey": false,
          "notNull": true
        }
      },
      "indexes": {
        "property_images_property_id_idx": {
          "name": "property_images_property_id_idx",
          "columns": [
            {
              "expression": "propertyId",
              "isExpression": false,
              "asc": true,
              "nulls": "last"
            }
          ],
          "isUnique": false,
          "concurrently": false,
          "method": "btree",
          "with": {}
        }
      },
      "foreignKeys": {
        "property_images_propertyId_property_id_fk": {
          "name": "property_images_propertyId_property_id_fk",
          "tableFrom": "property_images",
          "tableTo": "property",
          "columnsFrom": [
            "propertyId"
          ],
          "columnsTo": [
            "id"
          ],
          "onDelete": "cascade",
          "onUpdate": "cascade"
        }
      },
      "compositePrimaryKeys": {},
      "uniqueConstraints": {},
      "policies": {},
      "checkConstraints": {},
      "isRLSEnabled": false
    },
    "public.property_location": {
      "name": "property_location",
      "schema": "",
      "columns": {
        "id": {
          "name": "id",
          "type": "uuid",
          "primaryKey": true,
          "notNull": true,
          "default": "gen_random_uuid()"
        },
        "propertyId": {
          "name": "propertyId",
          "type": "uuid",
          "primaryKey": false,
          "notNull": false
        },
        "lat": {
          "name": "lat",
          "type": "numeric(9, 6)",
          "primaryKey": false,
          "notNull": true
        },
        "lon": {
          "name": "lon",
          "type": "numeric(9, 6)",
          "primaryKey": false,
          "notNull": true
        }
      },
      "indexes": {
        "property_location_property_id_idx": {
          "name": "property_location_property_id_idx",
          "columns": [
            {
              "expression": "propertyId",
              "isExpression": false,
              "asc": true,
              "nulls": "last"
            }
          ],
          "isUnique": false,
          "concurrently": false,
          "method": "btree",
          "with": {}
        },
        "property_location_geo_idx": {
          "name": "property_location_geo_idx",
          "columns": [
            {
              "expression": "lat",
              "isExpression": false,
              "asc": true,
              "nulls": "last"
            },
            {
              "expression": "lon",
              "isExpression": false,
              "asc": true,
              "nulls": "last"
            }
          ],
          "isUnique": false,
          "concurrently": false,
          "method": "btree",
          "with": {}
        }
      },
      "foreignKeys": {
        "property_location_propertyId_property_id_fk": {
          "name": "property_location_propertyId_property_id_fk",
          "tableFrom": "property_location",
          "tableTo": "property",
          "columnsFrom": [
            "propertyId"
          ],
          "columnsTo": [
            "id"
          ],
          "onDelete": "cascade",
          "onUpdate": "cascade"
        }
      },
      "compositePrimaryKeys": {},
      "uniqueConstraints": {},
      "policies": {},
      "checkConstraints": {},
      "isRLSEnabled": false
    },
    "public.users": {
      "name": "users",
      "schema": "",
      "columns": {
        "id": {
          "name": "id",
          "type": "uuid",
          "primaryKey": true,
          "notNull": true,
          "default": "gen_random_uuid()"
        },
        "name": {
          "name": "name",
          "type": "text",
          "primaryKey": false,
          "notNull": true
        },
        "email": {
          "name": "email",
          "type": "text",
          "primaryKey": false,
          "notNull": true
        },
        "image": {
          "name": "image",
          "type": "text",
          "primaryKey": false,
          "notNull": false
        },
        "password": {
          "name": "password",
          "type": "text",
          "primaryKey": false,
          "notNull": false
        },
        "phone": {
          "name": "phone",
          "type": "text",
          "primaryKey": false,
          "notNull": false
        },
        "panNumber": {
          "name": "panNumber",
          "type": "text",
          "primaryKey": false,
          "notNull": false
        },
        "address": {
          "name": "address",
          "type": "text",
          "primaryKey": false,
          "notNull": false
        },
        "role": {
          "name": "role",
          "type": "role",
          "typeSchema": "public",
          "primaryKey": false,
          "notNull": false,
          "default": "'MEMBER'"
        },
        "created_at": {
          "name": "created_at",
          "type": "timestamp with time zone",
          "primaryKey": false,
          "notNull": false,
          "default": "now()"
        },
        "updated_at": {
          "name": "updated_at",
          "type": "timestamp with time zone",
          "primaryKey": false,
          "notNull": false,
          "default": "now()"
        }
      },
      "indexes": {
        "users_role_idx": {
          "name": "users_role_idx",
          "columns": [
            {
              "expression": "role",
              "isExpression": false,
              "asc": true,
              "nulls": "last"
            }
          ],
          "isUnique": false,
          "concurrently": false,
          "method": "btree",
          "with": {}
        },
        "users_email_idx": {
          "name": "users_email_idx",
          "columns": [
            {
              "expression": "email",
              "isExpression": false,
              "asc": true,
              "nulls": "last"
            }
          ],
          "isUnique": false,
          "concurrently": false,
          "method": "btree",
          "with": {}
        },
        "users_pan_no_idx": {
          "name": "users_pan_no_idx",
          "columns": [
            {
              "expression": "panNumber",
              "isExpression": false,
              "asc": true,
              "nulls": "last"
            }
          ],
          "isUnique": false,
          "concurrently": false,
          "method": "btree",
          "with": {}
        }
      },
      "foreignKeys": {},
      "compositePrimaryKeys": {},
      "uniqueConstraints": {
        "users_email_unique": {
          "name": "users_email_unique",
          "nullsNotDistinct": false,
          "columns": [
            "email"
          ]
        }
      },
      "policies": {},
      "checkConstraints": {},
      "isRLSEnabled": false
    }
  },
  "enums": {
    "public.role": {
      "name": "role",
      "schema": "public",
      "values": [
        "SUPER_ADMIN",
        "ADMIN",
        "MEMBER"
      ]
    }
  },
  "schemas": {},
  "sequences": {},
  "roles": {},
  "policies": {},
  "views": {},
  "_meta": {
    "columns": {},
    "schemas": {},
    "tables": {}
  }
}